Workbook

Sheet Inputs
A1: Bloomberg factor vol data pull
A3: Start date | B3: 42005
A4: End date (blank = today)
A6: Fields | B6: PX_LAST | C6: 30DAY_IMPVOL_100.0%MNY_DF | D6: 1M_PUT_IMP_VOL_25DELTA_DFLT | E6: CUR_MKT_CAP | F6: BEST_PE_RATIO | G6: PE_RATIO | H6: PX_TO_BOOK_RATIO | I6: EV_TO_T12M_EBITDA | J6: RETURN_COM_EQY | K6: TOT_DEBT_TO_TOT_EQY | L6: BEST_EPS
A8: How to use | B8: Type tickers in column A and an optional peer group in column D (yellow). Rows 11-14 are an example peer group; overwrite them.
B9: Set the dates in B3:B4, then Bloomberg tab > Refresh Workbook. Each ticker fills its own block on the Data tab. Fields in row 6 can be swapped (check FLDS <GO>).
A10: Ticker | B10: Yellow key | C10: Bloomberg security | D10: Peer group | E10: GICS sector | F10: GICS industry | G10: Data tab column
A11: SNDK | B11: US Equity | C11: =IF(A11="","",A11&" "&B11) | D11: Storage | E11: =IF(C11="","",BDP(C11,"GICS_SECTOR_NAME")) | F11: =IF(C11="","",BDP(C11,"GICS_INDUSTRY_NAME")) | G11: A
A12: WDC | B12: US Equity | C12: =IF(A12="","",A12&" "&B12) | D12: Storage | E12: =IF(C12="","",BDP(C12,"GICS_SECTOR_NAME")) | F12: =IF(C12="","",BDP(C12,"GICS_INDUSTRY_NAME")) | G12: N
A13: STX | B13: US Equity | C13: =IF(A13="","",A13&" "&B13) | D13: Storage | E13: =IF(C13="","",BDP(C13,"GICS_SECTOR_NAME")) | F13: =IF(C13="","",BDP(C13,"GICS_INDUSTRY_NAME")) | G13: AA
A14: MU | B14: US Equity | C14: =IF(A14="","",A14&" "&B14) | D14: Storage | E14: =IF(C14="","",BDP(C14,"GICS_SECTOR_NAME")) | F14: =IF(C14="","",BDP(C14,"GICS_INDUSTRY_NAME")) | G14: AN
B15: US Equity | C15: =IF(A15="","",A15&" "&B15) | E15: =IF(C15="","",BDP(C15,"GICS_SECTOR_NAME")) | F15: =IF(C15="","",BDP(C15,"GICS_INDUSTRY_NAME")) | G15: BA
B16: US Equity | C16: =IF(A16="","",A16&" "&B16) | E16: =IF(C16="","",BDP(C16,"GICS_SECTOR_NAME")) | F16: =IF(C16="","",BDP(C16,"GICS_INDUSTRY_NAME")) | G16: BN
B17: US Equity | C17: =IF(A17="","",A17&" "&B17) | E17: =IF(C17="","",BDP(C17,"GICS_SECTOR_NAME")) | F17: =IF(C17="","",BDP(C17,"GICS_INDUSTRY_NAME")) | G17: CA
B18: US Equity | C18: =IF(A18="","",A18&" "&B18) | E18: =IF(C18="","",BDP(C18,"GICS_SECTOR_NAME")) | F18: =IF(C18="","",BDP(C18,"GICS_INDUSTRY_NAME")) | G18: CN
B19: US Equity | C19: =IF(A19="","",A19&" "&B19) | E19: =IF(C19="","",BDP(C19,"GICS_SECTOR_NAME")) | F19: =IF(C19="","",BDP(C19,"GICS_INDUSTRY_NAME")) | G19: DA
B20: US Equity | C20: =IF(A20="","",A20&" "&B20) | E20: =IF(C20="","",BDP(C20,"GICS_SECTOR_NAME")) | F20: =IF(C20="","",BDP(C20,"GICS_INDUSTRY_NAME")) | G20: DN
B21: US Equity | C21: =IF(A21="","",A21&" "&B21) | E21: =IF(C21="","",BDP(C21,"GICS_SECTOR_NAME")) | F21: =IF(C21="","",BDP(C21,"GICS_INDUSTRY_NAME")) | G21: EA
B22: US Equity | C22: =IF(A22="","",A22&" "&B22) | E22: =IF(C22="","",BDP(C22,"GICS_SECTOR_NAME")) | F22: =IF(C22="","",BDP(C22,"GICS_INDUSTRY_NAME")) | G22: EN
B23: US Equity | C23: =IF(A23="","",A23&" "&B23) | E23: =IF(C23="","",BDP(C23,"GICS_SECTOR_NAME")) | F23: =IF(C23="","",BDP(C23,"GICS_INDUSTRY_NAME")) | G23: FA
B24: US Equity | C24: =IF(A24="","",A24&" "&B24) | E24: =IF(C24="","",BDP(C24,"GICS_SECTOR_NAME")) | F24: =IF(C24="","",BDP(C24,"GICS_INDUSTRY_NAME")) | G24: FN
B25: US Equity | C25: =IF(A25="","",A25&" "&B25) | E25: =IF(C25="","",BDP(C25,"GICS_SECTOR_NAME")) | F25: =IF(C25="","",BDP(C25,"GICS_INDUSTRY_NAME")) | G25: GA
B26: US Equity | C26: =IF(A26="","",A26&" "&B26) | E26: =IF(C26="","",BDP(C26,"GICS_SECTOR_NAME")) | F26: =IF(C26="","",BDP(C26,"GICS_INDUSTRY_NAME")) | G26: GN
... B60: US Equity | C60: =IF(A60="","",A60&" "&B60) | E60: =IF(C60="","",BDP(C60,"GICS_SECTOR_NAME")) | F60: =IF(C60="","",BDP(C60,"GICS_INDUSTRY_NAME")) | G60: XN

Sheet Data
A1: =Inputs!$C$11 | N1: =Inputs!$C$12 | AA1: =Inputs!$C$13 | AN1: =Inputs!$C$14 | BA1: =Inputs!$C$15 | BN1: =Inputs!$C$16 | CA1: =Inputs!$C$17 | CN1: =Inputs!$C$18 | DA1: =Inputs!$C$19 | DN1: =Inputs!$C$20 | EA1: =Inputs!$C$21 | EN1: =Inputs!$C$22 | FA1: =Inputs!$C$23 | FN1: =Inputs!$C$24 | GA1: =Inputs!$C$25 | GN1: =Inputs!$C$26 | HA1: =Inputs!$C$27 | HN1: =Inputs!$C$28 | IA1: =Inputs!$C$29 | IN1: =Inputs!$C$30 | JA1: =Inputs!$C$31 | JN1: =Inputs!$C$32 | KA1: =Inputs!$C$33 | KN1: =Inputs!$C$34 | LA1: =Inputs!$C$35 | LN1: =Inputs!$C$36 | MA1: =Inputs!$C$37 | MN1: =Inputs!$C$38 | NA1: =Inputs!$C$39 | NN1: =Inputs!$C$40 | OA1: =Inputs!$C$41 | ON1: =Inputs!$C$42 | PA1: =Inputs!$C$43 | PN1: =Inputs!$C$44 | QA1: =Inputs!$C$45 | QN1: =Inputs!$C$46 | RA1: =Inputs!$C$47 | RN1: =Inputs!$C$48 | SA1: =Inputs!$C$49 | SN1: =Inputs!$C$50 | TA1: =Inputs!$C$51 | TN1: =Inputs!$C$52 | UA1: =Inputs!$C$53 | UN1: =Inputs!$C$54 | VA1: =Inputs!$C$55 | VN1: =Inputs!$C$56 | WA1: =Inputs!$C$57 | WN1: =Inputs!$C$58 | XA1: =Inputs!$C$59 | XN1: =Inputs!$C$60
A2: Date | B2: =Inputs!B$6 | C2: =Inputs!C$6 | D2: =Inputs!D$6 | E2: =Inputs!E$6 | F2: =Inputs!F$6 | G2: =Inputs!G$6 | H2: =Inputs!H$6 | I2: =Inputs!I$6 | ... L2: =Inputs!L$6 | N2: Date | O2: =Inputs!B$6 | P2: =Inputs!C$6 | Q2: =Inputs!D$6 | R2: =Inputs!E$6 | S2: =Inputs!F$6 | T2: =Inputs!G$6 | U2: =Inputs!H$6 | V2: =Inputs!I$6 | ... Y2: =Inputs!L$6 | AA2: Date | AB2: =Inputs!B$6 | AC2: =Inputs!C$6 | AD2: =Inputs!D$6 | AE2: =Inputs!E$6 | AF2: =Inputs!F$6 | AG2: =Inputs!G$6 | AH2: =Inputs!H$6 | AI2: =Inputs!I$6 | ... AL2: =Inputs!L$6 | AN2: Date | AO2: =Inputs!B$6 | AP2: =Inputs!C$6 | AQ2: =Inputs!D$6 | AR2: =Inputs!E$6 | AS2: =Inputs!F$6 | AT2: =Inputs!G$6 | AU2: =Inputs!H$6 | AV2: =Inputs!I$6 | ... AY2: =Inputs!L$6 | BA2: Date | BB2: =Inputs!B$6 | BC2: =Inputs!C$6 | BD2: =Inputs!D$6 | BE2: =Inputs!E$6 | BF2: =Inputs!F$6 | BG2: =Inputs!G$6 | BH2: =Inputs!H$6 | BI2: =Inputs!I$6 | ... BL2: =Inputs!L$6 | BN2: Date | BO2: =Inputs!B$6 | BP2: =Inputs!C$6 | BQ2: =Inputs!D$6 | BR2: =Inputs!E$6 | BS2: =Inputs!F$6 | BT2: =Inputs!G$6 | BU2: =Inputs!H$6 | BV2: =Inputs!I$6 | ... BY2: =Inputs!L$6 | CA2: Date | CB2: =Inputs!B$6 | CC2: =Inputs!C$6 | CD2: =Inputs!D$6 | CE2: =Inputs!E$6 | CF2: =Inputs!F$6 | CG2: =Inputs!G$6 | CH2: =Inputs!H$6 | CI2: =Inputs!I$6 | ... CL2: =Inputs!L$6 | CN2: Date | CO2: =Inputs!B$6 | CP2: =Inputs!C$6 | CQ2: =Inputs!D$6 | CR2: =Inputs!E$6 | CS2: =Inputs!F$6 | CT2: =Inputs!G$6 | CU2: =Inputs!H$6 | CV2: =Inputs!I$6 | ... CY2: =Inputs!L$6 | DA2: Date | DB2: =Inputs!B$6 | DC2: =Inputs!C$6 | DD2: =Inputs!D$6 | DE2: =Inputs!E$6 | DF2: =Inputs!F$6 | DG2: =Inputs!G$6 | DH2: =Inputs!H$6 | DI2: =Inputs!I$6 | ... DL2: =Inputs!L$6 | DN2: Date | DO2: =Inputs!B$6 | DP2: =Inputs!C$6 | DQ2: =Inputs!D$6 | DR2: =Inputs!E$6 | DS2: =Inputs!F$6 | DT2: =Inputs!G$6 | DU2: =Inputs!H$6 | DV2: =Inputs!I$6 | ... DY2: =Inputs!L$6 | EA2: Date | EB2: =Inputs!B$6 | EC2: =Inputs!C$6 | ED2: =Inputs!D$6 | EE2: =Inputs!E$6 | EF2: =Inputs!F$6 | EG2: =Inputs!G$6 | EH2: =Inputs!H$6 | EI2: =Inputs!I$6 | ... EL2: =Inputs!L$6 | EN2: Date | EO2: =Inputs!B$6 | EP2: =Inputs!C$6 | EQ2: =Inputs!D$6 | ER2: =Inputs!E$6 | ES2: =Inputs!F$6 | ET2: =Inputs!G$6 | EU2: =Inputs!H$6 | EV2: =Inputs!I$6 | ... EY2: =Inputs!L$6 | FA2: Date | FB2: =Inputs!B$6 | FC2: =Inputs!C$6 | FD2: =Inputs!D$6 | FE2: =Inputs!E$6 | FF2: =Inputs!F$6 | FG2: =Inputs!G$6 | FH2: =Inputs!H$6 | FI2: =Inputs!I$6 | ... FL2: =Inputs!L$6 | FN2: Date | FO2: =Inputs!B$6 | FP2: =Inputs!C$6 | FQ2: =Inputs!D$6 | FR2: =Inputs!E$6 | FS2: =Inputs!F$6 | FT2: =Inputs!G$6 | FU2: =Inputs!H$6 | FV2: =Inputs!I$6 | ... FY2: =Inputs!L$6 | GA2: Date | GB2: =Inputs!B$6 | GC2: =Inputs!C$6 | GD2: =Inputs!D$6 | GE2: =Inputs!E$6 | GF2: =Inputs!F$6 | GG2: =Inputs!G$6 | GH2: =Inputs!H$6 | GI2: =Inputs!I$6 | ... GL2: =Inputs!L$6 | GN2: Date | GO2: =Inputs!B$6 | GP2: =Inputs!C$6 | GQ2: =Inputs!D$6 | GR2: =Inputs!E$6 | GS2: =Inputs!F$6 | GT2: =Inputs!G$6 | GU2: =Inputs!H$6 | GV2: =Inputs!I$6 | ... GY2: =Inputs!L$6 | HA2: Date | HB2: =Inputs!B$6 | HC2: =Inputs!C$6 | HD2: =Inputs!D$6 | HE2: =Inputs!E$6 | HF2: =Inputs!F$6 | HG2: =Inputs!G$6 | HH2: =Inputs!H$6 | HI2: =Inputs!I$6 | ... HL2: =Inputs!L$6 | HN2: Date | HO2: =Inputs!B$6 | HP2: =Inputs!C$6 | HQ2: =Inputs!D$6 | HR2: =Inputs!E$6 | HS2: =Inputs!F$6 | HT2: =Inputs!G$6 | HU2: =Inputs!H$6 | HV2: =Inputs!I$6 | ... HY2: =Inputs!L$6 | IA2: Date | IB2: =Inputs!B$6 | IC2: =Inputs!C$6 | ID2: =Inputs!D$6 | IE2: =Inputs!E$6 | IF2: =Inputs!F$6 | IG2: =Inputs!G$6 | IH2: =Inputs!H$6 | II2: =Inputs!I$6 | ... IL2: =Inputs!L$6 | IN2: Date | IO2: =Inputs!B$6 | IP2: =Inputs!C$6 | IQ2: =Inputs!D$6 | IR2: =Inputs!E$6 | IS2: =Inputs!F$6 | IT2: =Inputs!G$6 | IU2: =Inputs!H$6 | IV2: =Inputs!I$6 | ... IY2: =Inputs!L$6 | JA2: Date | JB2: =Inputs!B$6 | JC2: =Inputs!C$6 | JD2: =Inputs!D$6 | JE2: =Inputs!E$6 | JF2: =Inputs!F$6 | JG2: =Inputs!G$6 | JH2: =Inputs!H$6 | JI2: =Inputs!I$6 | ... JL2: =Inputs!L$6 | JN2: Date | JO2: =Inputs!B$6 | JP2: =Inputs!C$6 | JQ2: =Inputs!D$6 | JR2: =Inputs!E$6 | JS2: =Inputs!F$6 | JT2: =Inputs!G$6 | JU2: =Inputs!H$6 | JV2: =Inputs!I$6 | ... JY2: =Inputs!L$6 | KA2: Date | KB2: =Inputs!B$6 | KC2: =Inputs!C$6 | KD2: =Inputs!D$6 | KE2: =Inputs!E$6 | KF2: =Inputs!F$6 | KG2: =Inputs!G$6 | KH2: =Inputs!H$6 | KI2: =Inputs!I$6 | ... KL2: =Inputs!L$6 | KN2: Date | KO2: =Inputs!B$6 | KP2: =Inputs!C$6 | KQ2: =Inputs!D$6 | KR2: =Inputs!E$6 | KS2: =Inputs!F$6 | KT2: =Inputs!G$6 | KU2: =Inputs!H$6 | KV2: =Inputs!I$6 | ... KY2: =Inputs!L$6 | LA2: Date | LB2: =Inputs!B$6 | LC2: =Inputs!C$6 | LD2: =Inputs!D$6 | LE2: =Inputs!E$6 | LF2: =Inputs!F$6 | LG2: =Inputs!G$6 | LH2: =Inputs!H$6 | LI2: =Inputs!I$6 | ... LL2: =Inputs!L$6 | LN2: Date | LO2: =Inputs!B$6 | LP2: =Inputs!C$6 | LQ2: =Inputs!D$6 | LR2: =Inputs!E$6 | LS2: =Inputs!F$6 | LT2: =Inputs!G$6 | LU2: =Inputs!H$6 | LV2: =Inputs!I$6 | ... LY2: =Inputs!L$6 | MA2: Date | MB2: =Inputs!B$6 | MC2: =Inputs!C$6 | MD2: =Inputs!D$6 | ME2: =Inputs!E$6 | MF2: =Inputs!F$6 | MG2: =Inputs!G$6 | MH2: =Inputs!H$6 | MI2: =Inputs!I$6 | ... ML2: =Inputs!L$6 | MN2: Date | MO2: =Inputs!B$6 | MP2: =Inputs!C$6 | MQ2: =Inputs!D$6 | MR2: =Inputs!E$6 | MS2: =Inputs!F$6 | MT2: =Inputs!G$6 | MU2: =Inputs!H$6 | MV2: =Inputs!I$6 | ... MY2: =Inputs!L$6 | NA2: Date | NB2: =Inputs!B$6 | NC2: =Inputs!C$6 | ND2: =Inputs!D$6 | NE2: =Inputs!E$6 | NF2: =Inputs!F$6 | NG2: =Inputs!G$6 | NH2: =Inputs!H$6 | NI2: =Inputs!I$6 | ... NL2: =Inputs!L$6 | NN2: Date | NO2: =Inputs!B$6 | NP2: =Inputs!C$6 | NQ2: =Inputs!D$6 | NR2: =Inputs!E$6 | NS2: =Inputs!F$6 | NT2: =Inputs!G$6 | NU2: =Inputs!H$6 | NV2: =Inputs!I$6 | ... NY2: =Inputs!L$6 | OA2: Date | OB2: =Inputs!B$6 | OC2: =Inputs!C$6 | OD2: =Inputs!D$6 | OE2: =Inputs!E$6 | OF2: =Inputs!F$6 | OG2: =Inputs!G$6 | OH2: =Inputs!H$6 | OI2: =Inputs!I$6 | ... OL2: =Inputs!L$6 | ON2: Date | OO2: =Inputs!B$6 | OP2: =Inputs!C$6 | OQ2: =Inputs!D$6 | OR2: =Inputs!E$6 | OS2: =Inputs!F$6 | OT2: =Inputs!G$6 | OU2: =Inputs!H$6 | OV2: =Inputs!I$6 | ... OY2: =Inputs!L$6 | PA2: Date | PB2: =Inputs!B$6 | PC2: =Inputs!C$6 | PD2: =Inputs!D$6 | PE2: =Inputs!E$6 | PF2: =Inputs!F$6 | PG2: =Inputs!G$6 | PH2: =Inputs!H$6 | PI2: =Inputs!I$6 | ... PL2: =Inputs!L$6 | PN2: Date | PO2: =Inputs!B$6 | PP2: =Inputs!C$6 | PQ2: =Inputs!D$6 | PR2: =Inputs!E$6 | PS2: =Inputs!F$6 | PT2: =Inputs!G$6 | PU2: =Inputs!H$6 | PV2: =Inputs!I$6 | ... PY2: =Inputs!L$6 | QA2: Date | QB2: =Inputs!B$6 | QC2: =Inputs!C$6 | QD2: =Inputs!D$6 | QE2: =Inputs!E$6 | QF2: =Inputs!F$6 | QG2: =Inputs!G$6 | QH2: =Inputs!H$6 | QI2: =Inputs!I$6 | ... QL2: =Inputs!L$6 | QN2: Date | QO2: =Inputs!B$6 | QP2: =Inputs!C$6 | QQ2: =Inputs!D$6 | QR2: =Inputs!E$6 | QS2: =Inputs!F$6 | QT2: =Inputs!G$6 | QU2: =Inputs!H$6 | QV2: =Inputs!I$6 | ... QY2: =Inputs!L$6 | RA2: Date | RB2: =Inputs!B$6 | RC2: =Inputs!C$6 | RD2: =Inputs!D$6 | RE2: =Inputs!E$6 | RF2: =Inputs!F$6 | RG2: =Inputs!G$6 | RH2: =Inputs!H$6 | RI2: =Inputs!I$6 | ... RL2: =Inputs!L$6 | RN2: Date | RO2: =Inputs!B$6 | RP2: =Inputs!C$6 | RQ2: =Inputs!D$6 | RR2: =Inputs!E$6 | RS2: =Inputs!F$6 | RT2: =Inputs!G$6 | RU2: =Inputs!H$6 | RV2: =Inputs!I$6 | ... RY2: =Inputs!L$6 | SA2: Date | SB2: =Inputs!B$6 | SC2: =Inputs!C$6 | SD2: =Inputs!D$6 | SE2: =Inputs!E$6 | SF2: =Inputs!F$6 | SG2: =Inputs!G$6 | SH2: =Inputs!H$6 | SI2: =Inputs!I$6 | ... SL2: =Inputs!L$6 | SN2: Date | SO2: =Inputs!B$6 | SP2: =Inputs!C$6 | SQ2: =Inputs!D$6 | SR2: =Inputs!E$6 | SS2: =Inputs!F$6 | ST2: =Inputs!G$6 | SU2: =Inputs!H$6 | SV2: =Inputs!I$6 | ... SY2: =Inputs!L$6 | TA2: Date | TB2: =Inputs!B$6 | TC2: =Inputs!C$6 | TD2: =Inputs!D$6 | TE2: =Inputs!E$6 | TF2: =Inputs!F$6 | TG2: =Inputs!G$6 | TH2: =Inputs!H$6 | TI2: =Inputs!I$6 | ... TL2: =Inputs!L$6 | TN2: Date | TO2: =Inputs!B$6 | TP2: =Inputs!C$6 | TQ2: =Inputs!D$6 | TR2: =Inputs!E$6 | TS2: =Inputs!F$6 | TT2: =Inputs!G$6 | TU2: =Inputs!H$6 | TV2: =Inputs!I$6 | ... TY2: =Inputs!L$6 | UA2: Date | UB2: =Inputs!B$6 | UC2: =Inputs!C$6 | UD2: =Inputs!D$6 | UE2: =Inputs!E$6 | UF2: =Inputs!F$6 | UG2: =Inputs!G$6 | UH2: =Inputs!H$6 | UI2: =Inputs!I$6 | ... UL2: =Inputs!L$6 | UN2: Date | UO2: =Inputs!B$6 | UP2: =Inputs!C$6 | UQ2: =Inputs!D$6 | UR2: =Inputs!E$6 | US2: =Inputs!F$6 | UT2: =Inputs!G$6 | UU2: =Inputs!H$6 | UV2: =Inputs!I$6 | ... UY2: =Inputs!L$6 | VA2: Date | VB2: =Inputs!B$6 | VC2: =Inputs!C$6 | VD2: =Inputs!D$6 | VE2: =Inputs!E$6 | VF2: =Inputs!F$6 | VG2: =Inputs!G$6 | VH2: =Inputs!H$6 | VI2: =Inputs!I$6 | ... VL2: =Inputs!L$6 | VN2: Date | VO2: =Inputs!B$6 | VP2: =Inputs!C$6 | VQ2: =Inputs!D$6 | VR2: =Inputs!E$6 | VS2: =Inputs!F$6 | VT2: =Inputs!G$6 | VU2: =Inputs!H$6 | VV2: =Inputs!I$6 | ... VY2: =Inputs!L$6 | WA2: Date | WB2: =Inputs!B$6 | WC2: =Inputs!C$6 | WD2: =Inputs!D$6 | WE2: =Inputs!E$6 | WF2: =Inputs!F$6 | WG2: =Inputs!G$6 | WH2: =Inputs!H$6 | WI2: =Inputs!I$6 | ... WL2: =Inputs!L$6 | WN2: Date | WO2: =Inputs!B$6 | WP2: =Inputs!C$6 | WQ2: =Inputs!D$6 | WR2: =Inputs!E$6 | WS2: =Inputs!F$6 | WT2: =Inputs!G$6 | WU2: =Inputs!H$6 | WV2: =Inputs!I$6 | ... WY2: =Inputs!L$6 | XA2: Date | XB2: =Inputs!B$6 | XC2: =Inputs!C$6 | XD2: =Inputs!D$6 | XE2: =Inputs!E$6 | XF2: =Inputs!F$6 | XG2: =Inputs!G$6 | XH2: =Inputs!H$6 | XI2: =Inputs!I$6 | ... XL2: =Inputs!L$6 | XN2: Date | XO2: =Inputs!B$6 | XP2: =Inputs!C$6 | XQ2: =Inputs!D$6 | XR2: =Inputs!E$6 | XS2: =Inputs!F$6 | XT2: =Inputs!G$6 | XU2: =Inputs!H$6 | XV2: =Inputs!I$6 | ... XY2: =Inputs!L$6
A3: =IF(Inputs!$C$11="","",BDH(Inputs!$C$11,Inputs!$B$6:$L$6,Inputs!$B$3,IF(Inputs!$B$4="","",Inputs!$B$4),"Dir=V","Days=T","Fill=P")) | N3: =IF(Inputs!$C$12="","",BDH(Inputs!$C$12,Inputs!$B$6:$L$6,Inputs!$B$3,IF(Inputs!$B$4="","",Inputs!$B$4),"Dir=V","Days=T","Fill=P")) | AA3: =IF(Inputs!$C$13="","",BDH(Inputs!$C$13,Inputs!$B$6:$L$6,Inputs!$B$3,IF(Inputs!$B$4="","",Inputs!$B$4),"Dir=V","Days=T","Fill=P")) | AN3: =IF(Inputs!$C$14="","",BDH(Inputs!$C$14,Inputs!$B$6:$L$6,Inputs!$B$3,IF(Inputs!$B$4="","",Inputs!$B$4),"Dir=V","Days=T","Fill=P")) | BA3: =IF(Inputs!$C$15="","",BDH(Inputs!$C$15,Inputs!$B$6:$L$6,Inputs!$B$3,IF(Inputs!$B$4="","",Inputs!$B$4),"Dir=V","Days=T","Fill=P")) | BN3: =IF(Inputs!$C$16="","",BDH(Inputs!$C$16,Inputs!$B$6:$L$6,Inputs!$B$3,IF(Inputs!$B$4="","",Inputs!$B$4),"Dir=V","Days=T","Fill=P")) | CA3: =IF(Inputs!$C$17="","",BDH(Inputs!$C$17,Inputs!$B$6:$L$6,Inputs!$B$3,IF(Inputs!$B$4="","",Inputs!$B$4),"Dir=V","Days=T","Fill=P")) | CN3: =IF(Inputs!$C$18="","",BDH(Inputs!$C$18,Inputs!$B$6:$L$6,Inputs!$B$3,IF(Inputs!$B$4="","",Inputs!$B$4),"Dir=V","Days=T","Fill=P")) | DA3: =IF(Inputs!$C$19="","",BDH(Inputs!$C$19,Inputs!$B$6:$L$6,Inputs!$B$3,IF(Inputs!$B$4="","",Inputs!$B$4),"Dir=V","Days=T","Fill=P")) | DN3: =IF(Inputs!$C$20="","",BDH(Inputs!$C$20,Inputs!$B$6:$L$6,Inputs!$B$3,IF(Inputs!$B$4="","",Inputs!$B$4),"Dir=V","Days=T","Fill=P")) | EA3: =IF(Inputs!$C$21="","",BDH(Inputs!$C$21,Inputs!$B$6:$L$6,Inputs!$B$3,IF(Inputs!$B$4="","",Inputs!$B$4),"Dir=V","Days=T","Fill=P")) | EN3: =IF(Inputs!$C$22="","",BDH(Inputs!$C$22,Inputs!$B$6:$L$6,Inputs!$B$3,IF(Inputs!$B$4="","",Inputs!$B$4),"Dir=V","Days=T","Fill=P")) | FA3: =IF(Inputs!$C$23="","",BDH(Inputs!$C$23,Inputs!$B$6:$L$6,Inputs!$B$3,IF(Inputs!$B$4="","",Inputs!$B$4),"Dir=V","Days=T","Fill=P")) | FN3: =IF(Inputs!$C$24="","",BDH(Inputs!$C$24,Inputs!$B$6:$L$6,Inputs!$B$3,IF(Inputs!$B$4="","",Inputs!$B$4),"Dir=V","Days=T","Fill=P")) | GA3: =IF(Inputs!$C$25="","",BDH(Inputs!$C$25,Inputs!$B$6:$L$6,Inputs!$B$3,IF(Inputs!$B$4="","",Inputs!$B$4),"Dir=V","Days=T","Fill=P")) | GN3: =IF(Inputs!$C$26="","",BDH(Inputs!$C$26,Inputs!$B$6:$L$6,Inputs!$B$3,IF(Inputs!$B$4="","",Inputs!$B$4),"Dir=V","Days=T","Fill=P")) | HA3: =IF(Inputs!$C$27="","",BDH(Inputs!$C$27,Inputs!$B$6:$L$6,Inputs!$B$3,IF(Inputs!$B$4="","",Inputs!$B$4),"Dir=V","Days=T","Fill=P")) | HN3: =IF(Inputs!$C$28="","",BDH(Inputs!$C$28,Inputs!$B$6:$L$6,Inputs!$B$3,IF(Inputs!$B$4="","",Inputs!$B$4),"Dir=V","Days=T","Fill=P")) | IA3: =IF(Inputs!$C$29="","",BDH(Inputs!$C$29,Inputs!$B$6:$L$6,Inputs!$B$3,IF(Inputs!$B$4="","",Inputs!$B$4),"Dir=V","Days=T","Fill=P")) | IN3: =IF(Inputs!$C$30="","",BDH(Inputs!$C$30,Inputs!$B$6:$L$6,Inputs!$B$3,IF(Inputs!$B$4="","",Inputs!$B$4),"Dir=V","Days=T","Fill=P")) | JA3: =IF(Inputs!$C$31="","",BDH(Inputs!$C$31,Inputs!$B$6:$L$6,Inputs!$B$3,IF(Inputs!$B$4="","",Inputs!$B$4),"Dir=V","Days=T","Fill=P")) | JN3: =IF(Inputs!$C$32="","",BDH(Inputs!$C$32,Inputs!$B$6:$L$6,Inputs!$B$3,IF(Inputs!$B$4="","",Inputs!$B$4),"Dir=V","Days=T","Fill=P")) | KA3: =IF(Inputs!$C$33="","",BDH(Inputs!$C$33,Inputs!$B$6:$L$6,Inputs!$B$3,IF(Inputs!$B$4="","",Inputs!$B$4),"Dir=V","Days=T","Fill=P")) | KN3: =IF(Inputs!$C$34="","",BDH(Inputs!$C$34,Inputs!$B$6:$L$6,Inputs!$B$3,IF(Inputs!$B$4="","",Inputs!$B$4),"Dir=V","Days=T","Fill=P")) | LA3: =IF(Inputs!$C$35="","",BDH(Inputs!$C$35,Inputs!$B$6:$L$6,Inputs!$B$3,IF(Inputs!$B$4="","",Inputs!$B$4),"Dir=V","Days=T","Fill=P")) | LN3: =IF(Inputs!$C$36="","",BDH(Inputs!$C$36,Inputs!$B$6:$L$6,Inputs!$B$3,IF(Inputs!$B$4="","",Inputs!$B$4),"Dir=V","Days=T","Fill=P")) | MA3: =IF(Inputs!$C$37="","",BDH(Inputs!$C$37,Inputs!$B$6:$L$6,Inputs!$B$3,IF(Inputs!$B$4="","",Inputs!$B$4),"Dir=V","Days=T","Fill=P")) | MN3: =IF(Inputs!$C$38="","",BDH(Inputs!$C$38,Inputs!$B$6:$L$6,Inputs!$B$3,IF(Inputs!$B$4="","",Inputs!$B$4),"Dir=V","Days=T","Fill=P")) | NA3: =IF(Inputs!$C$39="","",BDH(Inputs!$C$39,Inputs!$B$6:$L$6,Inputs!$B$3,IF(Inputs!$B$4="","",Inputs!$B$4),"Dir=V","Days=T","Fill=P")) | NN3: =IF(Inputs!$C$40="","",BDH(Inputs!$C$40,Inputs!$B$6:$L$6,Inputs!$B$3,IF(Inputs!$B$4="","",Inputs!$B$4),"Dir=V","Days=T","Fill=P")) | OA3: =IF(Inputs!$C$41="","",BDH(Inputs!$C$41,Inputs!$B$6:$L$6,Inputs!$B$3,IF(Inputs!$B$4="","",Inputs!$B$4),"Dir=V","Days=T","Fill=P")) | ON3: =IF(Inputs!$C$42="","",BDH(Inputs!$C$42,Inputs!$B$6:$L$6,Inputs!$B$3,IF(Inputs!$B$4="","",Inputs!$B$4),"Dir=V","Days=T","Fill=P")) | PA3: =IF(Inputs!$C$43="","",BDH(Inputs!$C$43,Inputs!$B$6:$L$6,Inputs!$B$3,IF(Inputs!$B$4="","",Inputs!$B$4),"Dir=V","Days=T","Fill=P")) | PN3: =IF(Inputs!$C$44="","",BDH(Inputs!$C$44,Inputs!$B$6:$L$6,Inputs!$B$3,IF(Inputs!$B$4="","",Inputs!$B$4),"Dir=V","Days=T","Fill=P")) | QA3: =IF(Inputs!$C$45="","",BDH(Inputs!$C$45,Inputs!$B$6:$L$6,Inputs!$B$3,IF(Inputs!$B$4="","",Inputs!$B$4),"Dir=V","Days=T","Fill=P")) | QN3: =IF(Inputs!$C$46="","",BDH(Inputs!$C$46,Inputs!$B$6:$L$6,Inputs!$B$3,IF(Inputs!$B$4="","",Inputs!$B$4),"Dir=V","Days=T","Fill=P")) | RA3: =IF(Inputs!$C$47="","",BDH(Inputs!$C$47,Inputs!$B$6:$L$6,Inputs!$B$3,IF(Inputs!$B$4="","",Inputs!$B$4),"Dir=V","Days=T","Fill=P")) | RN3: =IF(Inputs!$C$48="","",BDH(Inputs!$C$48,Inputs!$B$6:$L$6,Inputs!$B$3,IF(Inputs!$B$4="","",Inputs!$B$4),"Dir=V","Days=T","Fill=P")) | SA3: =IF(Inputs!$C$49="","",BDH(Inputs!$C$49,Inputs!$B$6:$L$6,Inputs!$B$3,IF(Inputs!$B$4="","",Inputs!$B$4),"Dir=V","Days=T","Fill=P")) | SN3: =IF(Inputs!$C$50="","",BDH(Inputs!$C$50,Inputs!$B$6:$L$6,Inputs!$B$3,IF(Inputs!$B$4="","",Inputs!$B$4),"Dir=V","Days=T","Fill=P")) | TA3: =IF(Inputs!$C$51="","",BDH(Inputs!$C$51,Inputs!$B$6:$L$6,Inputs!$B$3,IF(Inputs!$B$4="","",Inputs!$B$4),"Dir=V","Days=T","Fill=P")) | TN3: =IF(Inputs!$C$52="","",BDH(Inputs!$C$52,Inputs!$B$6:$L$6,Inputs!$B$3,IF(Inputs!$B$4="","",Inputs!$B$4),"Dir=V","Days=T","Fill=P")) | UA3: =IF(Inputs!$C$53="","",BDH(Inputs!$C$53,Inputs!$B$6:$L$6,Inputs!$B$3,IF(Inputs!$B$4="","",Inputs!$B$4),"Dir=V","Days=T","Fill=P")) | UN3: =IF(Inputs!$C$54="","",BDH(Inputs!$C$54,Inputs!$B$6:$L$6,Inputs!$B$3,IF(Inputs!$B$4="","",Inputs!$B$4),"Dir=V","Days=T","Fill=P")) | VA3: =IF(Inputs!$C$55="","",BDH(Inputs!$C$55,Inputs!$B$6:$L$6,Inputs!$B$3,IF(Inputs!$B$4="","",Inputs!$B$4),"Dir=V","Days=T","Fill=P")) | VN3: =IF(Inputs!$C$56="","",BDH(Inputs!$C$56,Inputs!$B$6:$L$6,Inputs!$B$3,IF(Inputs!$B$4="","",Inputs!$B$4),"Dir=V","Days=T","Fill=P")) | WA3: =IF(Inputs!$C$57="","",BDH(Inputs!$C$57,Inputs!$B$6:$L$6,Inputs!$B$3,IF(Inputs!$B$4="","",Inputs!$B$4),"Dir=V","Days=T","Fill=P")) | WN3: =IF(Inputs!$C$58="","",BDH(Inputs!$C$58,Inputs!$B$6:$L$6,Inputs!$B$3,IF(Inputs!$B$4="","",Inputs!$B$4),"Dir=V","Days=T","Fill=P")) | XA3: =IF(Inputs!$C$59="","",BDH(Inputs!$C$59,Inputs!$B$6:$L$6,Inputs!$B$3,IF(Inputs!$B$4="","",Inputs!$B$4),"Dir=V","Days=T","Fill=P")) | XN3: =IF(Inputs!$C$60="","",BDH(Inputs!$C$60,Inputs!$B$6:$L$6,Inputs!$B$3,IF(Inputs!$B$4="","",Inputs!$B$4),"Dir=V","Days=T","Fill=P"))

Sheet Fields
A1: Field | B1: Factor | C1: What it is
A2: PX_LAST | B2: Price | C2: Last price
A3: 30DAY_IMPVOL_100.0%MNY_DF | B3: Vol | C3: 30-day at-the-money implied vol, in % points
A4: 1M_PUT_IMP_VOL_25DELTA_DFLT | B4: Vol | C4: 1-month 25-delta put implied vol (downside skew), in % points
A5: CUR_MKT_CAP | B5: Size | C5: Market cap, in millions
A6: BEST_PE_RATIO | B6: Value | C6: Forward P/E on consensus EPS (blended next 12 months)
A7: PE_RATIO | B7: Value | C7: Trailing P/E
A8: PX_TO_BOOK_RATIO | B8: Value | C8: Price to book
A9: EV_TO_T12M_EBITDA | B9: Value | C9: Enterprise value to trailing 12-month EBITDA
A10: RETURN_COM_EQY | B10: Quality | C10: Return on common equity, in %
A11: TOT_DEBT_TO_TOT_EQY | B11: Quality | C11: Total debt to total equity, in %
A12: BEST_EPS | B12: Estimates | C12: Consensus EPS (blended next 12 months); watch for revisions
A14: Notes
A15: Field names come from Bloomberg user forums and docs; confirm each in FLDS <GO> before backtesting.
A16: Vol fields are in percentage points (25 = 25%).
A17: GICS sector and industry (BDP) are today's classification, not point-in-time.
A18: Fundamental fields in BDH change on report dates; check FLDS for the as-of convention so the backtest only uses figures known at the time.
A19: BDH options: Dir=V (dates down), Days=T (trading days), Fill=P (carry last value over gaps).
A20: If a block stays blank after refresh, remove the IF( wrapper so the cell is just =BDH(...).
